{"Id": "157", "MuseumId": "787", "Title": "OVERASSELT", "SubTitle": "Agrarisch Museum 'De Garstkamp", "Description": "De Garstkamp\r\n\r\n\r\nDe collectie geeft een representatief beeld van alle landbouwwerktuigen en gereedschappen die in het begin van deze eeuw in ons land, en speciaal in de streek rond Nijmegen, in gebruik zijn geweest. Er is e", "ImageUrl": "//cdn.museum.nl/cards/700x394/gif2jpg/9306_logo_uitsnede_2.jpg", "HasPromotions": "false", "IsPromotion": "false", "IsParticipant": "false", "EndDate": null, "DetailUrl": "/museum/Agrarisch+Museum+%27De+Garstkamp%27/Agrarisch+Museum+De+Garstkamp.aspx", "MagazineTheme": null, "MagazineThemeTitle": null, "City": null, "Address": null, "Type": "1", "IsKidsproof": null, "Longitude": "5.7875066", "Latitude": "51.7643469", "MapUrl": "http://maps.google.nl/maps?q=Locatie%C2%A0van%C2%A0OVERASSELT%4051.7643469,5.7875066&hl=nl&ie=UTF8&t=m&om=1&z=12"}