{"Id": "382", "MuseumId": "1115", "Title": "VALKENBURG", "SubTitle": "Kasteelru\u00efne / Fluweelengrot V", "Description": "Kasteelru&iuml;ne en Fluweelengrot Valkenburg\r\n\r\n\r\nOntdek de geheimen van deze unieke middeleeuwse dubbelattractie?!\r\n\r\nRidders en jonkvrouwen, belegeraars en veroveraars, geheime vluchtgangen naar het onderaards gangenstels", "ImageUrl": "//cdn.museum.nl/cards/700x394/plaatjesbank/kasteelgrot kasteel ruine 9769/9769_ruine.jpg", "HasPromotions": "false", "IsPromotion": "false", "IsParticipant": "false", "EndDate": null, "DetailUrl": "/museum/Kasteelru%c3%afne+%2f+Fluweelengrot+Valkenburg/Kasteelru%c3%afne+%26+Fluweelengrot+Valkenburg.aspx", "MagazineTheme": null, "MagazineThemeTitle": null, "City": null, "Address": null, "Type": "1", "IsKidsproof": null, "Longitude": null, "Latitude": null, "MapUrl": null}