{"Id": "441", "MuseumId": "1049", "Title": "HEESWIJK-DINTHER", "SubTitle": "Meierijsche Museumboerderij", "Description": "Meierijsche Museumboerderij\r\n\r\n\r\nHet museum omvat het boerderijgebouw met inventaris, de inrichting van erf en erfbeplanting. De totaliteit geeft een beeld van de eenvoudige woon-, werk- en levenswijze van een doorsnee boere", "ImageUrl": "//cdn.museum.nl/cards/700x394/plaatjesbank/museumboerderij weeswijk 9672/9672_interieur2.jpg", "HasPromotions": "false", "IsPromotion": "false", "IsParticipant": "false", "EndDate": null, "DetailUrl": "/museum/Meierijsche+Museumboerderij/Meierijsche+Museumboerderij.aspx", "MagazineTheme": null, "MagazineThemeTitle": null, "City": null, "Address": null, "Type": "1", "IsKidsproof": null, "Longitude": "5.4746358", "Latitude": "51.6656485", "MapUrl": "http://maps.google.nl/maps?q=Locatie%C2%A0van%C2%A0HEESWIJK-DINTHER%4051.6656485,5.4746358&hl=nl&ie=UTF8&t=m&om=1&z=12"}