{"Id": "479", "MuseumId": "127", "Title": "BROEK OP LANGEDIJK", "SubTitle": "Museum Broeker Veiling", "Description": "x", "ImageUrl": "//cdn.museum.nl/cards/700x394/1eb20b92-8404-47f8-83d4-75d072e55567\\broekerveiling anwb.jpg", "HasPromotions": "false", "IsPromotion": "false", "IsParticipant": "true", "EndDate": null, "DetailUrl": "/museum/Museum+Broeker+Veiling/Museum+Broeker+Veiling.aspx", "MagazineTheme": null, "MagazineThemeTitle": null, "City": null, "Address": null, "Type": "1", "IsKidsproof": null, "Longitude": "4.8073217", "Latitude": "52.6800385", "MapUrl": "http://maps.google.nl/maps?q=Locatie%C2%A0van%C2%A0BROEK+OP+LANGEDIJK%4052.6800385,4.8073217&hl=nl&ie=UTF8&t=m&om=1&z=12"}